tagmatcher/__init__.py
tag_matcher-0.0.5.dist-info/LICENSE
tag_matcher-0.0.5.dist-info/METADATA
tag_matcher-0.0.5.dist-info/WHEEL
tag_matcher-0.0.5.dist-info/top_level.txt
tag_matcher-0.0.5.dist-info/RECORD
