Metadata-Version: 2.1
Name: tag-matcher
Version: 0.0.5
Summary: A lightweight tag matcher
Home-page: https://github.com/jmfiola/tag-matcher
Author: Jacob Fiola
Author-email: jmfiola21@gmail.com
License: MIT
Requires-Python: >=3.1
License-File: LICENSE
